{
  "detail_id": 5166846,
  "metadata": {
    "ivr_number": "5166846",
    "permit_type": "Early AssistanceEA-Zoning & Inf. Bur.- w/mtg",
    "work_description": "We request to vacate the section of ROW known as SE 94th Ave (Property ID R666826), bordered to the north by Property ID R221696 and R221677, bordered to the east by the I-205 Freeway, Bicycle trail and Max, bordered to the south by SE Knapp Street, and bordered to the West by Property ID R221679, R221678, and R221680. We also request to vacate the section of ROW piece of Knapp Street bordered to the north by SE 94th Street (Property ID R666826), bordered to the east by the I-205 Freeway, Bicycle trail and Max line, bordered to the south by the continuation of SE Knapp Street and bordered to the West by Property ID R221679.",
    "address": null,
    "setup_date": "2025-07-01",
    "under_review_date": "2025-07-01",
    "issue_date": null,
    "final_date": null,
    "status": "Completed"
  },
  "activities": [
    {
      "activity_name": "R-O-W Acquisition",
      "activity_type": "Transportation",
      "must_check": "Y",
      "activity_status": "Completed",
      "last_activity_date": "2025-08-18",
      "goal_date": null,
      "completed_date": "2025-08-18",
      "staff_contact": "Lindahl,Lance   503-823-7465"
    },
    {
      "activity_name": "Tree Code - EA Response",
      "activity_type": "Trees",
      "must_check": "Y",
      "activity_status": "Completed",
      "last_activity_date": "2025-07-29",
      "goal_date": null,
      "completed_date": "2025-07-29",
      "staff_contact": "Olson,Neil   971-480-0805"
    },
    {
      "activity_name": "Intake-EA",
      "activity_type": "Land Use Services",
      "must_check": "Y",
      "activity_status": "Completed",
      "last_activity_date": "2025-07-08",
      "goal_date": null,
      "completed_date": "2025-07-08",
      "staff_contact": "Duncan,Elizabeth   503-865-6524"
    },
    {
      "activity_name": "BDS LUS - EA Response",
      "activity_type": "Land Use Services",
      "must_check": "Y",
      "activity_status": "Completed",
      "last_activity_date": "2025-08-05",
      "goal_date": null,
      "completed_date": "2025-08-05",
      "staff_contact": "Williams,Sean   503-865-6441"
    },
    {
      "activity_name": "Mail Appt Summary",
      "activity_type": "Land Use Services",
      "must_check": "Y",
      "activity_status": "Completed",
      "last_activity_date": "2025-08-18",
      "goal_date": null,
      "completed_date": "2025-08-18",
      "staff_contact": "LAND USE REVIEW"
    },
    {
      "activity_name": "Site Dev Review - EA mtg",
      "activity_type": "Site Development",
      "must_check": "Y",
      "activity_status": "Completed",
      "last_activity_date": "2025-07-30",
      "goal_date": null,
      "completed_date": "2025-07-30",
      "staff_contact": "Wells,Kevin   503-823-5618"
    },
    {
      "activity_name": "Site Dev Review - EA Response",
      "activity_type": "Site Development",
      "must_check": "Y",
      "activity_status": "Completed",
      "last_activity_date": "2025-08-12",
      "goal_date": null,
      "completed_date": "2025-08-12",
      "staff_contact": "Wells,Kevin   503-823-5618"
    },
    {
      "activity_name": "BES Syst Dev - EA mtg",
      "activity_type": "Environmental Services",
      "must_check": "Y",
      "activity_status": "Completed",
      "last_activity_date": "2025-07-29",
      "goal_date": null,
      "completed_date": "2025-07-29",
      "staff_contact": "Ruth,Ella   503-823-8068"
    },
    {
      "activity_name": "BES Syst Dev - EA Response",
      "activity_type": "Environmental Services",
      "must_check": "Y",
      "activity_status": "Completed",
      "last_activity_date": "2025-08-12",
      "goal_date": null,
      "completed_date": "2025-08-12",
      "staff_contact": "Ruth,Ella   503-823-8068"
    },
    {
      "activity_name": "BES PW - EA mtg",
      "activity_type": "Environmental Services",
      "must_check": "Y",
      "activity_status": "Completed",
      "last_activity_date": "2025-07-30",
      "goal_date": null,
      "completed_date": "2025-07-24",
      "staff_contact": "Duval,Andre   503-823-7214"
    },
    {
      "activity_name": "BES PW - EA Response",
      "activity_type": "Environmental Services",
      "must_check": "Y",
      "activity_status": "Completed",
      "last_activity_date": "2025-08-05",
      "goal_date": null,
      "completed_date": "2025-08-05",
      "staff_contact": "Duval,Andre   503-823-7214"
    },
    {
      "activity_name": "PBOT Dev Rev - EA mtg",
      "activity_type": "Transportation",
      "must_check": "Y",
      "activity_status": "Completed",
      "last_activity_date": "2025-07-22",
      "goal_date": null,
      "completed_date": "2025-07-22",
      "staff_contact": "Mann,Tyler   503-865-6444"
    },
    {
      "activity_name": "PBOT Dev Rev - EA Response",
      "activity_type": "Transportation",
      "must_check": "Y",
      "activity_status": "Completed",
      "last_activity_date": "2025-07-29",
      "goal_date": null,
      "completed_date": "2025-07-29",
      "staff_contact": "Mann,Tyler   503-865-6444"
    },
    {
      "activity_name": "PBOT PW - EA mtg",
      "activity_type": "Transportation",
      "must_check": "Y",
      "activity_status": "Open",
      "last_activity_date": "2025-07-08",
      "goal_date": "2025-07-24",
      "completed_date": null,
      "staff_contact": "PDOT PW Plan Reviewer"
    },
    {
      "activity_name": "Water PW - EA Response",
      "activity_type": "Water Bureau",
      "must_check": "Y",
      "activity_status": "Completed",
      "last_activity_date": "2025-08-04",
      "goal_date": null,
      "completed_date": "2025-08-04",
      "staff_contact": "Vittori,Bryan   971-917-5458"
    },
    {
      "activity_name": "Cancel Folder",
      "activity_type": "Process Managment",
      "must_check": "N",
      "activity_status": "Open",
      "last_activity_date": "2025-06-30",
      "goal_date": null,
      "completed_date": null,
      "staff_contact": ""
    },
    {
      "activity_name": "Put on Hold",
      "activity_type": "Process Managment",
      "must_check": "N",
      "activity_status": "Open",
      "last_activity_date": "2025-06-30",
      "goal_date": null,
      "completed_date": null,
      "staff_contact": ""
    },
    {
      "activity_name": "Remove Hold",
      "activity_type": "Process Managment",
      "must_check": "N",
      "activity_status": "Open",
      "last_activity_date": "2025-06-30",
      "goal_date": null,
      "completed_date": null,
      "staff_contact": ""
    }
  ]
}