{
  "detail_id": 5190015,
  "metadata": {
    "ivr_number": "5190015",
    "permit_type": "Code ComplianceZoning",
    "work_description": "Complaint Rcvd: WWP - Excavation w/out permit",
    "address": null,
    "setup_date": "2025-09-11",
    "under_review_date": "2025-09-11",
    "issue_date": null,
    "final_date": null,
    "status": "Request"
  },
  "activities": [
    {
      "activity_name": "Inspection - CC",
      "activity_type": "Request",
      "must_check": "N",
      "activity_status": "Open",
      "last_activity_date": "2025-09-11",
      "goal_date": "2025-09-17",
      "completed_date": null,
      "staff_contact": "Seward,Michelle   503-823-8167"
    },
    {
      "activity_name": "Close - CC",
      "activity_type": "Request",
      "must_check": "Y",
      "activity_status": "Open",
      "last_activity_date": "2025-09-11",
      "goal_date": null,
      "completed_date": null,
      "staff_contact": ""
    },
    {
      "activity_name": "Mailed Notices- CC",
      "activity_type": "Under Inspection",
      "must_check": "Y",
      "activity_status": "Open",
      "last_activity_date": "2025-09-11",
      "goal_date": null,
      "completed_date": null,
      "staff_contact": "Seward,Michelle   503-823-8167"
    },
    {
      "activity_name": "CC - Admin Review",
      "activity_type": "Under Inspection",
      "must_check": "N",
      "activity_status": "Open",
      "last_activity_date": "2025-09-11",
      "goal_date": null,
      "completed_date": null,
      "staff_contact": ""
    }
  ]
}